sphinx_nbblog/__about__.py
sphinx_nbblog/__init__.py
sphinx_nbblog/extension.py
sphinx_nbblog/tags.py
sphinx_nbblog-0.3.0.dist-info/METADATA
sphinx_nbblog-0.3.0.dist-info/WHEEL
sphinx_nbblog-0.3.0.dist-info/licenses/LICENSE.txt
sphinx_nbblog-0.3.0.dist-info/RECORD
