Metadata-Version: 2.1
Name: sphinx-nbblog
Version: 0.3.0
Summary: A small Sphinx extension to enable tags and archive in documentation such as for a blog.
Project-URL: Homepage, https://codeberg.org/bjorns/Sphinx-nbblog
Project-URL: Documentation, https://codeberg.org/bjorns/Sphinx-nbblog
Project-URL: Issues, https://codeberg.org/bjorns/Sphinx-nbblog/issues
Project-URL: Source, https://codeberg.org/bjorns/Sphinx-nbblog
Author-email: bjorns <bjorn@tauganet.io>
License-Expression: MIT
License-File: LICENSE.txt
Keywords: blog,extension,sphinx
Classifier: Development Status :: 4 - Beta
Classifier: License :: OSI Approved :: MIT License
Classifier: Programming Language :: Python
Classifier: Programming Language :: Python :: 3.9
Classifier: Programming Language :: Python :: 3.10
Classifier: Programming Language :: Python :: 3.11
Classifier: Programming Language :: Python :: Implementation :: CPython
Requires-Python: >=3.9
Requires-Dist: nbsphinx
Requires-Dist: sphinx
